<metadata__cache__entry>
  <version>5.2.0.0</version>
  <connectorName>MySQL_Configuration</connectorName>
  <metadataIo class="tree-map">
    <entry>
      <string>http://www.mulesoft.org/schema/mule/db/insert</string>
      <map>
        <entry>
          <string>Insert into SellTo_Srini(No,Name,City,Postcode,PhoneNumber,AccountStatusCode,BilltoCustomer,SalespersonCode,LastDateModified,PriceCardCode) values(#[payload.No],#[payload.Name],#[payload.City],#[payload.Postcode],#[payload.PhoneNumber],#[payload.AccountStatusCode],#[payload.BilltoCustomer],#[payload.SalespersonCode],#[payload.LastDateModified],#[payload.PriceCardCode])</string>
          <org.mule.tooling.metadata.cache.DefaultMetadataCacheEntry>
            <input class="org.mule.common.metadata.DefaultMetaData">
              <payload class="org.mule.common.metadata.DefaultDefinedMapMetaDataModel">
                <dataType>MAP</dataType>
                <metaDataModelPropertiesManager>
                  <properties/>
                </metaDataModelPropertiesManager>
                <fields>
                  <org.mule.common.metadata.DefaultMetaDataField>
                    <name>PriceCardCode</name>
                    <model class="org.mule.common.metadata.DefaultSimpleMetaDataModel">
                      <dataType>STRING</dataType>
                      <metaDataModelPropertiesManager>
                        <properties/>
                      </metaDataModelPropertiesManager>
                    </model>
                    <accessType>READ_WRITE</accessType>
                    <metaDataFieldPropertyManager>
                      <properties>
                        <org.mule.common.metadata.field.property.dsql.DsqlSelectMetaDataFieldProperty/>
                        <org.mule.common.metadata.field.property.dsql.DsqlWhereMetaDataFieldProperty/>
                        <org.mule.common.metadata.field.property.dsql.DsqlOrderMetaDataFieldProperty/>
                        <org.mule.common.metadata.field.property.dsql.DsqlQueryOperatorsMetaDataFieldProperty>
                          <supportedOperators>
                            <org.mule.common.query.expression.LessOperator/>
                            <org.mule.common.query.expression.LessOrEqualsOperator/>
                            <org.mule.common.query.expression.EqualsOperator/>
                            <org.mule.common.query.expression.GreaterOperator/>
                            <org.mule.common.query.expression.GreaterOrEqualsOperator/>
                            <org.mule.common.query.expression.NotEqualsOperator/>
                            <org.mule.common.query.expression.LikeOperator/>
                          </supportedOperators>
                        </org.mule.common.metadata.field.property.dsql.DsqlQueryOperatorsMetaDataFieldProperty>
                      </properties>
                    </metaDataFieldPropertyManager>
                  </org.mule.common.metadata.DefaultMetaDataField>
                  <org.mule.common.metadata.DefaultMetaDataField>
                    <name>No</name>
                    <model class="org.mule.common.metadata.DefaultSimpleMetaDataModel" reference="../../org.mule.common.metadata.DefaultMetaDataField/model"/>
                    <accessType>READ_WRITE</accessType>
                    <metaDataFieldPropertyManager>
                      <properties>
                        <org.mule.common.metadata.field.property.dsql.DsqlSelectMetaDataFieldProperty/>
                        <org.mule.common.metadata.field.property.dsql.DsqlWhereMetaDataFieldProperty/>
                        <org.mule.common.metadata.field.property.dsql.DsqlOrderMetaDataFieldProperty/>
                        <org.mule.common.metadata.field.property.dsql.DsqlQueryOperatorsMetaDataFieldProperty>
                          <supportedOperators>
                            <org.mule.common.query.expression.LessOperator/>
                            <org.mule.common.query.expression.LessOrEqualsOperator/>
                            <org.mule.common.query.expression.EqualsOperator/>
                            <org.mule.common.query.expression.GreaterOperator/>
                            <org.mule.common.query.expression.GreaterOrEqualsOperator/>
                            <org.mule.common.query.expression.NotEqualsOperator/>
                            <org.mule.common.query.expression.LikeOperator/>
                          </supportedOperators>
                        </org.mule.common.metadata.field.property.dsql.DsqlQueryOperatorsMetaDataFieldProperty>
                      </properties>
                    </metaDataFieldPropertyManager>
                  </org.mule.common.metadata.DefaultMetaDataField>
                  <org.mule.common.metadata.DefaultMetaDataField>
                    <name>AccountStatusCode</name>
                    <model class="org.mule.common.metadata.DefaultSimpleMetaDataModel" reference="../../org.mule.common.metadata.DefaultMetaDataField/model"/>
                    <accessType>READ_WRITE</accessType>
                    <metaDataFieldPropertyManager>
                      <properties>
                        <org.mule.common.metadata.field.property.dsql.DsqlSelectMetaDataFieldProperty/>
                        <org.mule.common.metadata.field.property.dsql.DsqlWhereMetaDataFieldProperty/>
                        <org.mule.common.metadata.field.property.dsql.DsqlOrderMetaDataFieldProperty/>
                        <org.mule.common.metadata.field.property.dsql.DsqlQueryOperatorsMetaDataFieldProperty>
                          <supportedOperators>
                            <org.mule.common.query.expression.LessOperator/>
                            <org.mule.common.query.expression.LessOrEqualsOperator/>
                            <org.mule.common.query.expression.EqualsOperator/>
                            <org.mule.common.query.expression.GreaterOperator/>
                            <org.mule.common.query.expression.GreaterOrEqualsOperator/>
                            <org.mule.common.query.expression.NotEqualsOperator/>
                            <org.mule.common.query.expression.LikeOperator/>
                          </supportedOperators>
                        </org.mule.common.metadata.field.property.dsql.DsqlQueryOperatorsMetaDataFieldProperty>
                      </properties>
                    </metaDataFieldPropertyManager>
                  </org.mule.common.metadata.DefaultMetaDataField>
                  <org.mule.common.metadata.DefaultMetaDataField>
                    <name>LastDateModified</name>
                    <model class="org.mule.common.metadata.DefaultSimpleMetaDataModel" reference="../../org.mule.common.metadata.DefaultMetaDataField/model"/>
                    <accessType>READ_WRITE</accessType>
                    <metaDataFieldPropertyManager>
                      <properties>
                        <org.mule.common.metadata.field.property.dsql.DsqlSelectMetaDataFieldProperty/>
                        <org.mule.common.metadata.field.property.dsql.DsqlWhereMetaDataFieldProperty/>
                        <org.mule.common.metadata.field.property.dsql.DsqlOrderMetaDataFieldProperty/>
                        <org.mule.common.metadata.field.property.dsql.DsqlQueryOperatorsMetaDataFieldProperty>
                          <supportedOperators>
                            <org.mule.common.query.expression.LessOperator/>
                            <org.mule.common.query.expression.LessOrEqualsOperator/>
                            <org.mule.common.query.expression.EqualsOperator/>
                            <org.mule.common.query.expression.GreaterOperator/>
                            <org.mule.common.query.expression.GreaterOrEqualsOperator/>
                            <org.mule.common.query.expression.NotEqualsOperator/>
                            <org.mule.common.query.expression.LikeOperator/>
                          </supportedOperators>
                        </org.mule.common.metadata.field.property.dsql.DsqlQueryOperatorsMetaDataFieldProperty>
                      </properties>
                    </metaDataFieldPropertyManager>
                  </org.mule.common.metadata.DefaultMetaDataField>
                  <org.mule.common.metadata.DefaultMetaDataField>
                    <name>BilltoCustomer</name>
                    <model class="org.mule.common.metadata.DefaultSimpleMetaDataModel" reference="../../org.mule.common.metadata.DefaultMetaDataField/model"/>
                    <accessType>READ_WRITE</accessType>
                    <metaDataFieldPropertyManager>
                      <properties>
                        <org.mule.common.metadata.field.property.dsql.DsqlSelectMetaDataFieldProperty/>
                        <org.mule.common.metadata.field.property.dsql.DsqlWhereMetaDataFieldProperty/>
                        <org.mule.common.metadata.field.property.dsql.DsqlOrderMetaDataFieldProperty/>
                        <org.mule.common.metadata.field.property.dsql.DsqlQueryOperatorsMetaDataFieldProperty>
                          <supportedOperators>
                            <org.mule.common.query.expression.LessOperator/>
                            <org.mule.common.query.expression.LessOrEqualsOperator/>
                            <org.mule.common.query.expression.EqualsOperator/>
                            <org.mule.common.query.expression.GreaterOperator/>
                            <org.mule.common.query.expression.GreaterOrEqualsOperator/>
                            <org.mule.common.query.expression.NotEqualsOperator/>
                            <org.mule.common.query.expression.LikeOperator/>
                          </supportedOperators>
                        </org.mule.common.metadata.field.property.dsql.DsqlQueryOperatorsMetaDataFieldProperty>
                      </properties>
                    </metaDataFieldPropertyManager>
                  </org.mule.common.metadata.DefaultMetaDataField>
                  <org.mule.common.metadata.DefaultMetaDataField>
                    <name>PhoneNumber</name>
                    <model class="org.mule.common.metadata.DefaultSimpleMetaDataModel" reference="../../org.mule.common.metadata.DefaultMetaDataField/model"/>
                    <accessType>READ_WRITE</accessType>
                    <metaDataFieldPropertyManager>
                      <properties>
                        <org.mule.common.metadata.field.property.dsql.DsqlSelectMetaDataFieldProperty/>
                        <org.mule.common.metadata.field.property.dsql.DsqlWhereMetaDataFieldProperty/>
                        <org.mule.common.metadata.field.property.dsql.DsqlOrderMetaDataFieldProperty/>
                        <org.mule.common.metadata.field.property.dsql.DsqlQueryOperatorsMetaDataFieldProperty>
                          <supportedOperators>
                            <org.mule.common.query.expression.LessOperator/>
                            <org.mule.common.query.expression.LessOrEqualsOperator/>
                            <org.mule.common.query.expression.EqualsOperator/>
                            <org.mule.common.query.expression.GreaterOperator/>
                            <org.mule.common.query.expression.GreaterOrEqualsOperator/>
                            <org.mule.common.query.expression.NotEqualsOperator/>
                            <org.mule.common.query.expression.LikeOperator/>
                          </supportedOperators>
                        </org.mule.common.metadata.field.property.dsql.DsqlQueryOperatorsMetaDataFieldProperty>
                      </properties>
                    </metaDataFieldPropertyManager>
                  </org.mule.common.metadata.DefaultMetaDataField>
                  <org.mule.common.metadata.DefaultMetaDataField>
                    <name>City</name>
                    <model class="org.mule.common.metadata.DefaultSimpleMetaDataModel" reference="../../org.mule.common.metadata.DefaultMetaDataField/model"/>
                    <accessType>READ_WRITE</accessType>
                    <metaDataFieldPropertyManager>
                      <properties>
                        <org.mule.common.metadata.field.property.dsql.DsqlSelectMetaDataFieldProperty/>
                        <org.mule.common.metadata.field.property.dsql.DsqlWhereMetaDataFieldProperty/>
                        <org.mule.common.metadata.field.property.dsql.DsqlOrderMetaDataFieldProperty/>
                        <org.mule.common.metadata.field.property.dsql.DsqlQueryOperatorsMetaDataFieldProperty>
                          <supportedOperators>
                            <org.mule.common.query.expression.LessOperator/>
                            <org.mule.common.query.expression.LessOrEqualsOperator/>
                            <org.mule.common.query.expression.EqualsOperator/>
                            <org.mule.common.query.expression.GreaterOperator/>
                            <org.mule.common.query.expression.GreaterOrEqualsOperator/>
                            <org.mule.common.query.expression.NotEqualsOperator/>
                            <org.mule.common.query.expression.LikeOperator/>
                          </supportedOperators>
                        </org.mule.common.metadata.field.property.dsql.DsqlQueryOperatorsMetaDataFieldProperty>
                      </properties>
                    </metaDataFieldPropertyManager>
                  </org.mule.common.metadata.DefaultMetaDataField>
                  <org.mule.common.metadata.DefaultMetaDataField>
                    <name>SalespersonCode</name>
                    <model class="org.mule.common.metadata.DefaultSimpleMetaDataModel" reference="../../org.mule.common.metadata.DefaultMetaDataField/model"/>
                    <accessType>READ_WRITE</accessType>
                    <metaDataFieldPropertyManager>
                      <properties>
                        <org.mule.common.metadata.field.property.dsql.DsqlSelectMetaDataFieldProperty/>
                        <org.mule.common.metadata.field.property.dsql.DsqlWhereMetaDataFieldProperty/>
                        <org.mule.common.metadata.field.property.dsql.DsqlOrderMetaDataFieldProperty/>
                        <org.mule.common.metadata.field.property.dsql.DsqlQueryOperatorsMetaDataFieldProperty>
                          <supportedOperators>
                            <org.mule.common.query.expression.LessOperator/>
                            <org.mule.common.query.expression.LessOrEqualsOperator/>
                            <org.mule.common.query.expression.EqualsOperator/>
                            <org.mule.common.query.expression.GreaterOperator/>
                            <org.mule.common.query.expression.GreaterOrEqualsOperator/>
                            <org.mule.common.query.expression.NotEqualsOperator/>
                            <org.mule.common.query.expression.LikeOperator/>
                          </supportedOperators>
                        </org.mule.common.metadata.field.property.dsql.DsqlQueryOperatorsMetaDataFieldProperty>
                      </properties>
                    </metaDataFieldPropertyManager>
                  </org.mule.common.metadata.DefaultMetaDataField>
                  <org.mule.common.metadata.DefaultMetaDataField>
                    <name>Postcode</name>
                    <model class="org.mule.common.metadata.DefaultSimpleMetaDataModel" reference="../../org.mule.common.metadata.DefaultMetaDataField/model"/>
                    <accessType>READ_WRITE</accessType>
                    <metaDataFieldPropertyManager>
                      <properties>
                        <org.mule.common.metadata.field.property.dsql.DsqlSelectMetaDataFieldProperty/>
                        <org.mule.common.metadata.field.property.dsql.DsqlWhereMetaDataFieldProperty/>
                        <org.mule.common.metadata.field.property.dsql.DsqlOrderMetaDataFieldProperty/>
                        <org.mule.common.metadata.field.property.dsql.DsqlQueryOperatorsMetaDataFieldProperty>
                          <supportedOperators>
                            <org.mule.common.query.expression.LessOperator/>
                            <org.mule.common.query.expression.LessOrEqualsOperator/>
                            <org.mule.common.query.expression.EqualsOperator/>
                            <org.mule.common.query.expression.GreaterOperator/>
                            <org.mule.common.query.expression.GreaterOrEqualsOperator/>
                            <org.mule.common.query.expression.NotEqualsOperator/>
                            <org.mule.common.query.expression.LikeOperator/>
                          </supportedOperators>
                        </org.mule.common.metadata.field.property.dsql.DsqlQueryOperatorsMetaDataFieldProperty>
                      </properties>
                    </metaDataFieldPropertyManager>
                  </org.mule.common.metadata.DefaultMetaDataField>
                  <org.mule.common.metadata.DefaultMetaDataField>
                    <name>Name</name>
                    <model class="org.mule.common.metadata.DefaultSimpleMetaDataModel" reference="../../org.mule.common.metadata.DefaultMetaDataField/model"/>
                    <accessType>READ_WRITE</accessType>
                    <metaDataFieldPropertyManager>
                      <properties>
                        <org.mule.common.metadata.field.property.dsql.DsqlSelectMetaDataFieldProperty/>
                        <org.mule.common.metadata.field.property.dsql.DsqlWhereMetaDataFieldProperty/>
                        <org.mule.common.metadata.field.property.dsql.DsqlOrderMetaDataFieldProperty/>
                        <org.mule.common.metadata.field.property.dsql.DsqlQueryOperatorsMetaDataFieldProperty>
                          <supportedOperators>
                            <org.mule.common.query.expression.LessOperator/>
                            <org.mule.common.query.expression.LessOrEqualsOperator/>
                            <org.mule.common.query.expression.EqualsOperator/>
                            <org.mule.common.query.expression.GreaterOperator/>
                            <org.mule.common.query.expression.GreaterOrEqualsOperator/>
                            <org.mule.common.query.expression.NotEqualsOperator/>
                            <org.mule.common.query.expression.LikeOperator/>
                          </supportedOperators>
                        </org.mule.common.metadata.field.property.dsql.DsqlQueryOperatorsMetaDataFieldProperty>
                      </properties>
                    </metaDataFieldPropertyManager>
                  </org.mule.common.metadata.DefaultMetaDataField>
                </fields>
              </payload>
              <properties>
                <entry>
                  <org.mule.common.metadata.MetaDataPropertyScope>FLOW</org.mule.common.metadata.MetaDataPropertyScope>
                  <org.mule.common.metadata.MetaDataProperties>
                    <fields/>
                  </org.mule.common.metadata.MetaDataProperties>
                </entry>
                <entry>
                  <org.mule.common.metadata.MetaDataPropertyScope>INBOUND</org.mule.common.metadata.MetaDataPropertyScope>
                  <org.mule.common.metadata.MetaDataProperties>
                    <fields/>
                  </org.mule.common.metadata.MetaDataProperties>
                </entry>
                <entry>
                  <org.mule.common.metadata.MetaDataPropertyScope>RECORD</org.mule.common.metadata.MetaDataPropertyScope>
                  <org.mule.common.metadata.MetaDataProperties>
                    <fields/>
                  </org.mule.common.metadata.MetaDataProperties>
                </entry>
                <entry>
                  <org.mule.common.metadata.MetaDataPropertyScope>OUTBOUND</org.mule.common.metadata.MetaDataPropertyScope>
                  <org.mule.common.metadata.MetaDataProperties>
                    <fields/>
                  </org.mule.common.metadata.MetaDataProperties>
                </entry>
                <entry>
                  <org.mule.common.metadata.MetaDataPropertyScope>SESSION</org.mule.common.metadata.MetaDataPropertyScope>
                  <org.mule.common.metadata.MetaDataProperties>
                    <fields/>
                  </org.mule.common.metadata.MetaDataProperties>
                </entry>
              </properties>
            </input>
            <output class="org.mule.common.metadata.DefaultMetaData">
              <payload class="org.mule.common.metadata.DefaultSimpleMetaDataModel">
                <dataType>DOUBLE</dataType>
                <metaDataModelPropertiesManager>
                  <properties/>
                </metaDataModelPropertiesManager>
              </payload>
              <properties>
                <entry>
                  <org.mule.common.metadata.MetaDataPropertyScope>FLOW</org.mule.common.metadata.MetaDataPropertyScope>
                  <org.mule.common.metadata.MetaDataProperties>
                    <fields/>
                  </org.mule.common.metadata.MetaDataProperties>
                </entry>
                <entry>
                  <org.mule.common.metadata.MetaDataPropertyScope>INBOUND</org.mule.common.metadata.MetaDataPropertyScope>
                  <org.mule.common.metadata.MetaDataProperties>
                    <fields/>
                  </org.mule.common.metadata.MetaDataProperties>
                </entry>
                <entry>
                  <org.mule.common.metadata.MetaDataPropertyScope>RECORD</org.mule.common.metadata.MetaDataPropertyScope>
                  <org.mule.common.metadata.MetaDataProperties>
                    <fields/>
                  </org.mule.common.metadata.MetaDataProperties>
                </entry>
                <entry>
                  <org.mule.common.metadata.MetaDataPropertyScope>OUTBOUND</org.mule.common.metadata.MetaDataPropertyScope>
                  <org.mule.common.metadata.MetaDataProperties>
                    <fields/>
                  </org.mule.common.metadata.MetaDataProperties>
                </entry>
                <entry>
                  <org.mule.common.metadata.MetaDataPropertyScope>SESSION</org.mule.common.metadata.MetaDataPropertyScope>
                  <org.mule.common.metadata.MetaDataProperties>
                    <fields/>
                  </org.mule.common.metadata.MetaDataProperties>
                </entry>
              </properties>
            </output>
          </org.mule.tooling.metadata.cache.DefaultMetadataCacheEntry>
        </entry>
        <entry>
          <string>Insert into BillTo_Srini (no,name) values(#[payload.no]</string>
          <org.mule.tooling.metadata.cache.DefaultMetadataCacheEntry>
            <input class="org.mule.common.metadata.DefaultMetaData">
              <payload class="org.mule.common.metadata.DefaultDefinedMapMetaDataModel">
                <dataType>MAP</dataType>
                <metaDataModelPropertiesManager>
                  <properties/>
                </metaDataModelPropertiesManager>
                <fields>
                  <org.mule.common.metadata.DefaultMetaDataField>
                    <name>no</name>
                    <model class="org.mule.common.metadata.DefaultSimpleMetaDataModel">
                      <dataType>STRING</dataType>
                      <metaDataModelPropertiesManager>
                        <properties/>
                      </metaDataModelPropertiesManager>
                    </model>
                    <accessType>READ_WRITE</accessType>
                    <metaDataFieldPropertyManager>
                      <properties>
                        <org.mule.common.metadata.field.property.dsql.DsqlSelectMetaDataFieldProperty/>
                        <org.mule.common.metadata.field.property.dsql.DsqlWhereMetaDataFieldProperty/>
                        <org.mule.common.metadata.field.property.dsql.DsqlOrderMetaDataFieldProperty/>
                        <org.mule.common.metadata.field.property.dsql.DsqlQueryOperatorsMetaDataFieldProperty>
                          <supportedOperators>
                            <org.mule.common.query.expression.LessOperator/>
                            <org.mule.common.query.expression.LessOrEqualsOperator/>
                            <org.mule.common.query.expression.EqualsOperator/>
                            <org.mule.common.query.expression.GreaterOperator/>
                            <org.mule.common.query.expression.GreaterOrEqualsOperator/>
                            <org.mule.common.query.expression.NotEqualsOperator/>
                            <org.mule.common.query.expression.LikeOperator/>
                          </supportedOperators>
                        </org.mule.common.metadata.field.property.dsql.DsqlQueryOperatorsMetaDataFieldProperty>
                      </properties>
                    </metaDataFieldPropertyManager>
                  </org.mule.common.metadata.DefaultMetaDataField>
                </fields>
              </payload>
              <properties>
                <entry>
                  <org.mule.common.metadata.MetaDataPropertyScope>FLOW</org.mule.common.metadata.MetaDataPropertyScope>
                  <org.mule.common.metadata.MetaDataProperties>
                    <fields/>
                  </org.mule.common.metadata.MetaDataProperties>
                </entry>
                <entry>
                  <org.mule.common.metadata.MetaDataPropertyScope>INBOUND</org.mule.common.metadata.MetaDataPropertyScope>
                  <org.mule.common.metadata.MetaDataProperties>
                    <fields/>
                  </org.mule.common.metadata.MetaDataProperties>
                </entry>
                <entry>
                  <org.mule.common.metadata.MetaDataPropertyScope>RECORD</org.mule.common.metadata.MetaDataPropertyScope>
                  <org.mule.common.metadata.MetaDataProperties>
                    <fields/>
                  </org.mule.common.metadata.MetaDataProperties>
                </entry>
                <entry>
                  <org.mule.common.metadata.MetaDataPropertyScope>OUTBOUND</org.mule.common.metadata.MetaDataPropertyScope>
                  <org.mule.common.metadata.MetaDataProperties>
                    <fields/>
                  </org.mule.common.metadata.MetaDataProperties>
                </entry>
                <entry>
                  <org.mule.common.metadata.MetaDataPropertyScope>SESSION</org.mule.common.metadata.MetaDataPropertyScope>
                  <org.mule.common.metadata.MetaDataProperties>
                    <fields/>
                  </org.mule.common.metadata.MetaDataProperties>
                </entry>
              </properties>
            </input>
            <output class="org.mule.common.metadata.DefaultMetaData">
              <payload class="org.mule.common.metadata.DefaultSimpleMetaDataModel">
                <dataType>DOUBLE</dataType>
                <metaDataModelPropertiesManager>
                  <properties/>
                </metaDataModelPropertiesManager>
              </payload>
              <properties>
                <entry>
                  <org.mule.common.metadata.MetaDataPropertyScope>FLOW</org.mule.common.metadata.MetaDataPropertyScope>
                  <org.mule.common.metadata.MetaDataProperties>
                    <fields/>
                  </org.mule.common.metadata.MetaDataProperties>
                </entry>
                <entry>
                  <org.mule.common.metadata.MetaDataPropertyScope>INBOUND</org.mule.common.metadata.MetaDataPropertyScope>
                  <org.mule.common.metadata.MetaDataProperties>
                    <fields/>
                  </org.mule.common.metadata.MetaDataProperties>
                </entry>
                <entry>
                  <org.mule.common.metadata.MetaDataPropertyScope>RECORD</org.mule.common.metadata.MetaDataPropertyScope>
                  <org.mule.common.metadata.MetaDataProperties>
                    <fields/>
                  </org.mule.common.metadata.MetaDataProperties>
                </entry>
                <entry>
                  <org.mule.common.metadata.MetaDataPropertyScope>OUTBOUND</org.mule.common.metadata.MetaDataPropertyScope>
                  <org.mule.common.metadata.MetaDataProperties>
                    <fields/>
                  </org.mule.common.metadata.MetaDataProperties>
                </entry>
                <entry>
                  <org.mule.common.metadata.MetaDataPropertyScope>SESSION</org.mule.common.metadata.MetaDataPropertyScope>
                  <org.mule.common.metadata.MetaDataProperties>
                    <fields/>
                  </org.mule.common.metadata.MetaDataProperties>
                </entry>
              </properties>
            </output>
          </org.mule.tooling.metadata.cache.DefaultMetadataCacheEntry>
        </entry>
        <entry>
          <string>Insert into SellTo_Srini() values(#[payload.])</string>
          <org.mule.tooling.metadata.cache.DefaultMetadataCacheEntry>
            <input class="org.mule.common.metadata.DefaultMetaData">
              <payload class="org.mule.common.metadata.DefaultDefinedMapMetaDataModel">
                <dataType>MAP</dataType>
                <metaDataModelPropertiesManager>
                  <properties/>
                </metaDataModelPropertiesManager>
                <fields>
                  <org.mule.common.metadata.DefaultMetaDataField>
                    <name></name>
                    <model class="org.mule.common.metadata.DefaultSimpleMetaDataModel">
                      <dataType>STRING</dataType>
                      <metaDataModelPropertiesManager>
                        <properties/>
                      </metaDataModelPropertiesManager>
                    </model>
                    <accessType>READ_WRITE</accessType>
                    <metaDataFieldPropertyManager>
                      <properties>
                        <org.mule.common.metadata.field.property.dsql.DsqlSelectMetaDataFieldProperty/>
                        <org.mule.common.metadata.field.property.dsql.DsqlWhereMetaDataFieldProperty/>
                        <org.mule.common.metadata.field.property.dsql.DsqlOrderMetaDataFieldProperty/>
                        <org.mule.common.metadata.field.property.dsql.DsqlQueryOperatorsMetaDataFieldProperty>
                          <supportedOperators>
                            <org.mule.common.query.expression.LessOperator/>
                            <org.mule.common.query.expression.LessOrEqualsOperator/>
                            <org.mule.common.query.expression.EqualsOperator/>
                            <org.mule.common.query.expression.GreaterOperator/>
                            <org.mule.common.query.expression.GreaterOrEqualsOperator/>
                            <org.mule.common.query.expression.NotEqualsOperator/>
                            <org.mule.common.query.expression.LikeOperator/>
                          </supportedOperators>
                        </org.mule.common.metadata.field.property.dsql.DsqlQueryOperatorsMetaDataFieldProperty>
                      </properties>
                    </metaDataFieldPropertyManager>
                  </org.mule.common.metadata.DefaultMetaDataField>
                </fields>
              </payload>
              <properties>
                <entry>
                  <org.mule.common.metadata.MetaDataPropertyScope>FLOW</org.mule.common.metadata.MetaDataPropertyScope>
                  <org.mule.common.metadata.MetaDataProperties>
                    <fields/>
                  </org.mule.common.metadata.MetaDataProperties>
                </entry>
                <entry>
                  <org.mule.common.metadata.MetaDataPropertyScope>INBOUND</org.mule.common.metadata.MetaDataPropertyScope>
                  <org.mule.common.metadata.MetaDataProperties>
                    <fields/>
                  </org.mule.common.metadata.MetaDataProperties>
                </entry>
                <entry>
                  <org.mule.common.metadata.MetaDataPropertyScope>RECORD</org.mule.common.metadata.MetaDataPropertyScope>
                  <org.mule.common.metadata.MetaDataProperties>
                    <fields/>
                  </org.mule.common.metadata.MetaDataProperties>
                </entry>
                <entry>
                  <org.mule.common.metadata.MetaDataPropertyScope>OUTBOUND</org.mule.common.metadata.MetaDataPropertyScope>
                  <org.mule.common.metadata.MetaDataProperties>
                    <fields/>
                  </org.mule.common.metadata.MetaDataProperties>
                </entry>
                <entry>
                  <org.mule.common.metadata.MetaDataPropertyScope>SESSION</org.mule.common.metadata.MetaDataPropertyScope>
                  <org.mule.common.metadata.MetaDataProperties>
                    <fields/>
                  </org.mule.common.metadata.MetaDataProperties>
                </entry>
              </properties>
            </input>
            <output class="org.mule.common.metadata.DefaultMetaData">
              <payload class="org.mule.common.metadata.DefaultSimpleMetaDataModel">
                <dataType>DOUBLE</dataType>
                <metaDataModelPropertiesManager>
                  <properties/>
                </metaDataModelPropertiesManager>
              </payload>
              <properties>
                <entry>
                  <org.mule.common.metadata.MetaDataPropertyScope>FLOW</org.mule.common.metadata.MetaDataPropertyScope>
                  <org.mule.common.metadata.MetaDataProperties>
                    <fields/>
                  </org.mule.common.metadata.MetaDataProperties>
                </entry>
                <entry>
                  <org.mule.common.metadata.MetaDataPropertyScope>INBOUND</org.mule.common.metadata.MetaDataPropertyScope>
                  <org.mule.common.metadata.MetaDataProperties>
                    <fields/>
                  </org.mule.common.metadata.MetaDataProperties>
                </entry>
                <entry>
                  <org.mule.common.metadata.MetaDataPropertyScope>RECORD</org.mule.common.metadata.MetaDataPropertyScope>
                  <org.mule.common.metadata.MetaDataProperties>
                    <fields/>
                  </org.mule.common.metadata.MetaDataProperties>
                </entry>
                <entry>
                  <org.mule.common.metadata.MetaDataPropertyScope>OUTBOUND</org.mule.common.metadata.MetaDataPropertyScope>
                  <org.mule.common.metadata.MetaDataProperties>
                    <fields/>
                  </org.mule.common.metadata.MetaDataProperties>
                </entry>
                <entry>
                  <org.mule.common.metadata.MetaDataPropertyScope>SESSION</org.mule.common.metadata.MetaDataPropertyScope>
                  <org.mule.common.metadata.MetaDataProperties>
                    <fields/>
                  </org.mule.common.metadata.MetaDataProperties>
                </entry>
              </properties>
            </output>
          </org.mule.tooling.metadata.cache.DefaultMetadataCacheEntry>
        </entry>
        <entry>
          <string>Insert into Machine_Srini(No,MachineTypeCode,ConcessionType,CustomerCode,LocationOfService,InstalledDate) values(#[payload.no],#[payload.machineType],#[payload.concession],#[payload.customerNo],#[payload.location],#[payload.installedDate])</string>
          <org.mule.tooling.metadata.cache.DefaultMetadataCacheEntry>
            <input class="org.mule.common.metadata.DefaultMetaData">
              <payload class="org.mule.common.metadata.DefaultDefinedMapMetaDataModel">
                <dataType>MAP</dataType>
                <metaDataModelPropertiesManager>
                  <properties/>
                </metaDataModelPropertiesManager>
                <fields>
                  <org.mule.common.metadata.DefaultMetaDataField>
                    <name>no</name>
                    <model class="org.mule.common.metadata.DefaultSimpleMetaDataModel">
                      <dataType>STRING</dataType>
                      <metaDataModelPropertiesManager>
                        <properties/>
                      </metaDataModelPropertiesManager>
                    </model>
                    <accessType>READ_WRITE</accessType>
                    <metaDataFieldPropertyManager>
                      <properties>
                        <org.mule.common.metadata.field.property.dsql.DsqlSelectMetaDataFieldProperty/>
                        <org.mule.common.metadata.field.property.dsql.DsqlWhereMetaDataFieldProperty/>
                        <org.mule.common.metadata.field.property.dsql.DsqlOrderMetaDataFieldProperty/>
                        <org.mule.common.metadata.field.property.dsql.DsqlQueryOperatorsMetaDataFieldProperty>
                          <supportedOperators>
                            <org.mule.common.query.expression.LessOperator/>
                            <org.mule.common.query.expression.LessOrEqualsOperator/>
                            <org.mule.common.query.expression.EqualsOperator/>
                            <org.mule.common.query.expression.GreaterOperator/>
                            <org.mule.common.query.expression.GreaterOrEqualsOperator/>
                            <org.mule.common.query.expression.NotEqualsOperator/>
                            <org.mule.common.query.expression.LikeOperator/>
                          </supportedOperators>
                        </org.mule.common.metadata.field.property.dsql.DsqlQueryOperatorsMetaDataFieldProperty>
                      </properties>
                    </metaDataFieldPropertyManager>
                  </org.mule.common.metadata.DefaultMetaDataField>
                  <org.mule.common.metadata.DefaultMetaDataField>
                    <name>concession</name>
                    <model class="org.mule.common.metadata.DefaultSimpleMetaDataModel" reference="../../org.mule.common.metadata.DefaultMetaDataField/model"/>
                    <accessType>READ_WRITE</accessType>
                    <metaDataFieldPropertyManager>
                      <properties>
                        <org.mule.common.metadata.field.property.dsql.DsqlSelectMetaDataFieldProperty/>
                        <org.mule.common.metadata.field.property.dsql.DsqlWhereMetaDataFieldProperty/>
                        <org.mule.common.metadata.field.property.dsql.DsqlOrderMetaDataFieldProperty/>
                        <org.mule.common.metadata.field.property.dsql.DsqlQueryOperatorsMetaDataFieldProperty>
                          <supportedOperators>
                            <org.mule.common.query.expression.LessOperator/>
                            <org.mule.common.query.expression.LessOrEqualsOperator/>
                            <org.mule.common.query.expression.EqualsOperator/>
                            <org.mule.common.query.expression.GreaterOperator/>
                            <org.mule.common.query.expression.GreaterOrEqualsOperator/>
                            <org.mule.common.query.expression.NotEqualsOperator/>
                            <org.mule.common.query.expression.LikeOperator/>
                          </supportedOperators>
                        </org.mule.common.metadata.field.property.dsql.DsqlQueryOperatorsMetaDataFieldProperty>
                      </properties>
                    </metaDataFieldPropertyManager>
                  </org.mule.common.metadata.DefaultMetaDataField>
                  <org.mule.common.metadata.DefaultMetaDataField>
                    <name>installedDate</name>
                    <model class="org.mule.common.metadata.DefaultSimpleMetaDataModel" reference="../../org.mule.common.metadata.DefaultMetaDataField/model"/>
                    <accessType>READ_WRITE</accessType>
                    <metaDataFieldPropertyManager>
                      <properties>
                        <org.mule.common.metadata.field.property.dsql.DsqlSelectMetaDataFieldProperty/>
                        <org.mule.common.metadata.field.property.dsql.DsqlWhereMetaDataFieldProperty/>
                        <org.mule.common.metadata.field.property.dsql.DsqlOrderMetaDataFieldProperty/>
                        <org.mule.common.metadata.field.property.dsql.DsqlQueryOperatorsMetaDataFieldProperty>
                          <supportedOperators>
                            <org.mule.common.query.expression.LessOperator/>
                            <org.mule.common.query.expression.LessOrEqualsOperator/>
                            <org.mule.common.query.expression.EqualsOperator/>
                            <org.mule.common.query.expression.GreaterOperator/>
                            <org.mule.common.query.expression.GreaterOrEqualsOperator/>
                            <org.mule.common.query.expression.NotEqualsOperator/>
                            <org.mule.common.query.expression.LikeOperator/>
                          </supportedOperators>
                        </org.mule.common.metadata.field.property.dsql.DsqlQueryOperatorsMetaDataFieldProperty>
                      </properties>
                    </metaDataFieldPropertyManager>
                  </org.mule.common.metadata.DefaultMetaDataField>
                  <org.mule.common.metadata.DefaultMetaDataField>
                    <name>location</name>
                    <model class="org.mule.common.metadata.DefaultSimpleMetaDataModel" reference="../../org.mule.common.metadata.DefaultMetaDataField/model"/>
                    <accessType>READ_WRITE</accessType>
                    <metaDataFieldPropertyManager>
                      <properties>
                        <org.mule.common.metadata.field.property.dsql.DsqlSelectMetaDataFieldProperty/>
                        <org.mule.common.metadata.field.property.dsql.DsqlWhereMetaDataFieldProperty/>
                        <org.mule.common.metadata.field.property.dsql.DsqlOrderMetaDataFieldProperty/>
                        <org.mule.common.metadata.field.property.dsql.DsqlQueryOperatorsMetaDataFieldProperty>
                          <supportedOperators>
                            <org.mule.common.query.expression.LessOperator/>
                            <org.mule.common.query.expression.LessOrEqualsOperator/>
                            <org.mule.common.query.expression.EqualsOperator/>
                            <org.mule.common.query.expression.GreaterOperator/>
                            <org.mule.common.query.expression.GreaterOrEqualsOperator/>
                            <org.mule.common.query.expression.NotEqualsOperator/>
                            <org.mule.common.query.expression.LikeOperator/>
                          </supportedOperators>
                        </org.mule.common.metadata.field.property.dsql.DsqlQueryOperatorsMetaDataFieldProperty>
                      </properties>
                    </metaDataFieldPropertyManager>
                  </org.mule.common.metadata.DefaultMetaDataField>
                  <org.mule.common.metadata.DefaultMetaDataField>
                    <name>machineType</name>
                    <model class="org.mule.common.metadata.DefaultSimpleMetaDataModel" reference="../../org.mule.common.metadata.DefaultMetaDataField/model"/>
                    <accessType>READ_WRITE</accessType>
                    <metaDataFieldPropertyManager>
                      <properties>
                        <org.mule.common.metadata.field.property.dsql.DsqlSelectMetaDataFieldProperty/>
                        <org.mule.common.metadata.field.property.dsql.DsqlWhereMetaDataFieldProperty/>
                        <org.mule.common.metadata.field.property.dsql.DsqlOrderMetaDataFieldProperty/>
                        <org.mule.common.metadata.field.property.dsql.DsqlQueryOperatorsMetaDataFieldProperty>
                          <supportedOperators>
                            <org.mule.common.query.expression.LessOperator/>
                            <org.mule.common.query.expression.LessOrEqualsOperator/>
                            <org.mule.common.query.expression.EqualsOperator/>
                            <org.mule.common.query.expression.GreaterOperator/>
                            <org.mule.common.query.expression.GreaterOrEqualsOperator/>
                            <org.mule.common.query.expression.NotEqualsOperator/>
                            <org.mule.common.query.expression.LikeOperator/>
                          </supportedOperators>
                        </org.mule.common.metadata.field.property.dsql.DsqlQueryOperatorsMetaDataFieldProperty>
                      </properties>
                    </metaDataFieldPropertyManager>
                  </org.mule.common.metadata.DefaultMetaDataField>
                  <org.mule.common.metadata.DefaultMetaDataField>
                    <name>customerNo</name>
                    <model class="org.mule.common.metadata.DefaultSimpleMetaDataModel" reference="../../org.mule.common.metadata.DefaultMetaDataField/model"/>
                    <accessType>READ_WRITE</accessType>
                    <metaDataFieldPropertyManager>
                      <properties>
                        <org.mule.common.metadata.field.property.dsql.DsqlSelectMetaDataFieldProperty/>
                        <org.mule.common.metadata.field.property.dsql.DsqlWhereMetaDataFieldProperty/>
                        <org.mule.common.metadata.field.property.dsql.DsqlOrderMetaDataFieldProperty/>
                        <org.mule.common.metadata.field.property.dsql.DsqlQueryOperatorsMetaDataFieldProperty>
                          <supportedOperators>
                            <org.mule.common.query.expression.LessOperator/>
                            <org.mule.common.query.expression.LessOrEqualsOperator/>
                            <org.mule.common.query.expression.EqualsOperator/>
                            <org.mule.common.query.expression.GreaterOperator/>
                            <org.mule.common.query.expression.GreaterOrEqualsOperator/>
                            <org.mule.common.query.expression.NotEqualsOperator/>
                            <org.mule.common.query.expression.LikeOperator/>
                          </supportedOperators>
                        </org.mule.common.metadata.field.property.dsql.DsqlQueryOperatorsMetaDataFieldProperty>
                      </properties>
                    </metaDataFieldPropertyManager>
                  </org.mule.common.metadata.DefaultMetaDataField>
                </fields>
              </payload>
              <properties>
                <entry>
                  <org.mule.common.metadata.MetaDataPropertyScope>FLOW</org.mule.common.metadata.MetaDataPropertyScope>
                  <org.mule.common.metadata.MetaDataProperties>
                    <fields/>
                  </org.mule.common.metadata.MetaDataProperties>
                </entry>
                <entry>
                  <org.mule.common.metadata.MetaDataPropertyScope>INBOUND</org.mule.common.metadata.MetaDataPropertyScope>
                  <org.mule.common.metadata.MetaDataProperties>
                    <fields/>
                  </org.mule.common.metadata.MetaDataProperties>
                </entry>
                <entry>
                  <org.mule.common.metadata.MetaDataPropertyScope>RECORD</org.mule.common.metadata.MetaDataPropertyScope>
                  <org.mule.common.metadata.MetaDataProperties>
                    <fields/>
                  </org.mule.common.metadata.MetaDataProperties>
                </entry>
                <entry>
                  <org.mule.common.metadata.MetaDataPropertyScope>OUTBOUND</org.mule.common.metadata.MetaDataPropertyScope>
                  <org.mule.common.metadata.MetaDataProperties>
                    <fields/>
                  </org.mule.common.metadata.MetaDataProperties>
                </entry>
                <entry>
                  <org.mule.common.metadata.MetaDataPropertyScope>SESSION</org.mule.common.metadata.MetaDataPropertyScope>
                  <org.mule.common.metadata.MetaDataProperties>
                    <fields/>
                  </org.mule.common.metadata.MetaDataProperties>
                </entry>
              </properties>
            </input>
            <output class="org.mule.common.metadata.DefaultMetaData">
              <payload class="org.mule.common.metadata.DefaultSimpleMetaDataModel">
                <dataType>DOUBLE</dataType>
                <metaDataModelPropertiesManager>
                  <properties/>
                </metaDataModelPropertiesManager>
              </payload>
              <properties>
                <entry>
                  <org.mule.common.metadata.MetaDataPropertyScope>FLOW</org.mule.common.metadata.MetaDataPropertyScope>
                  <org.mule.common.metadata.MetaDataProperties>
                    <fields/>
                  </org.mule.common.metadata.MetaDataProperties>
                </entry>
                <entry>
                  <org.mule.common.metadata.MetaDataPropertyScope>INBOUND</org.mule.common.metadata.MetaDataPropertyScope>
                  <org.mule.common.metadata.MetaDataProperties>
                    <fields/>
                  </org.mule.common.metadata.MetaDataProperties>
                </entry>
                <entry>
                  <org.mule.common.metadata.MetaDataPropertyScope>RECORD</org.mule.common.metadata.MetaDataPropertyScope>
                  <org.mule.common.metadata.MetaDataProperties>
                    <fields/>
                  </org.mule.common.metadata.MetaDataProperties>
                </entry>
                <entry>
                  <org.mule.common.metadata.MetaDataPropertyScope>OUTBOUND</org.mule.common.metadata.MetaDataPropertyScope>
                  <org.mule.common.metadata.MetaDataProperties>
                    <fields/>
                  </org.mule.common.metadata.MetaDataProperties>
                </entry>
                <entry>
                  <org.mule.common.metadata.MetaDataPropertyScope>SESSION</org.mule.common.metadata.MetaDataPropertyScope>
                  <org.mule.common.metadata.MetaDataProperties>
                    <fields/>
                  </org.mule.common.metadata.MetaDataProperties>
                </entry>
              </properties>
            </output>
          </org.mule.tooling.metadata.cache.DefaultMetadataCacheEntry>
        </entry>
        <entry>
          <string>Insert into BillTo_Srini (No,Name,PhoneNo,AccountStatusCode,LastDateModified,SalespersonCode) values(#[payload.no], #[payload.name], #[payload.phoneno],#[payload.accountstatuscode],#[payload.lmd],#[payload.salespersoncode])</string>
          <org.mule.tooling.metadata.cache.DefaultMetadataCacheEntry>
            <input class="org.mule.common.metadata.DefaultMetaData">
              <payload class="org.mule.common.metadata.DefaultDefinedMapMetaDataModel">
                <dataType>MAP</dataType>
                <metaDataModelPropertiesManager>
                  <properties/>
                </metaDataModelPropertiesManager>
                <fields>
                  <org.mule.common.metadata.DefaultMetaDataField>
                    <name>salespersoncode</name>
                    <model class="org.mule.common.metadata.DefaultSimpleMetaDataModel">
                      <dataType>STRING</dataType>
                      <metaDataModelPropertiesManager>
                        <properties/>
                      </metaDataModelPropertiesManager>
                    </model>
                    <accessType>READ_WRITE</accessType>
                    <metaDataFieldPropertyManager>
                      <properties>
                        <org.mule.common.metadata.field.property.dsql.DsqlSelectMetaDataFieldProperty/>
                        <org.mule.common.metadata.field.property.dsql.DsqlWhereMetaDataFieldProperty/>
                        <org.mule.common.metadata.field.property.dsql.DsqlOrderMetaDataFieldProperty/>
                        <org.mule.common.metadata.field.property.dsql.DsqlQueryOperatorsMetaDataFieldProperty>
                          <supportedOperators>
                            <org.mule.common.query.expression.LessOperator/>
                            <org.mule.common.query.expression.LessOrEqualsOperator/>
                            <org.mule.common.query.expression.EqualsOperator/>
                            <org.mule.common.query.expression.GreaterOperator/>
                            <org.mule.common.query.expression.GreaterOrEqualsOperator/>
                            <org.mule.common.query.expression.NotEqualsOperator/>
                            <org.mule.common.query.expression.LikeOperator/>
                          </supportedOperators>
                        </org.mule.common.metadata.field.property.dsql.DsqlQueryOperatorsMetaDataFieldProperty>
                      </properties>
                    </metaDataFieldPropertyManager>
                  </org.mule.common.metadata.DefaultMetaDataField>
                  <org.mule.common.metadata.DefaultMetaDataField>
                    <name>no</name>
                    <model class="org.mule.common.metadata.DefaultSimpleMetaDataModel" reference="../../org.mule.common.metadata.DefaultMetaDataField/model"/>
                    <accessType>READ_WRITE</accessType>
                    <metaDataFieldPropertyManager>
                      <properties>
                        <org.mule.common.metadata.field.property.dsql.DsqlSelectMetaDataFieldProperty/>
                        <org.mule.common.metadata.field.property.dsql.DsqlWhereMetaDataFieldProperty/>
                        <org.mule.common.metadata.field.property.dsql.DsqlOrderMetaDataFieldProperty/>
                        <org.mule.common.metadata.field.property.dsql.DsqlQueryOperatorsMetaDataFieldProperty>
                          <supportedOperators>
                            <org.mule.common.query.expression.LessOperator/>
                            <org.mule.common.query.expression.LessOrEqualsOperator/>
                            <org.mule.common.query.expression.EqualsOperator/>
                            <org.mule.common.query.expression.GreaterOperator/>
                            <org.mule.common.query.expression.GreaterOrEqualsOperator/>
                            <org.mule.common.query.expression.NotEqualsOperator/>
                            <org.mule.common.query.expression.LikeOperator/>
                          </supportedOperators>
                        </org.mule.common.metadata.field.property.dsql.DsqlQueryOperatorsMetaDataFieldProperty>
                      </properties>
                    </metaDataFieldPropertyManager>
                  </org.mule.common.metadata.DefaultMetaDataField>
                  <org.mule.common.metadata.DefaultMetaDataField>
                    <name>lmd</name>
                    <model class="org.mule.common.metadata.DefaultSimpleMetaDataModel" reference="../../org.mule.common.metadata.DefaultMetaDataField/model"/>
                    <accessType>READ_WRITE</accessType>
                    <metaDataFieldPropertyManager>
                      <properties>
                        <org.mule.common.metadata.field.property.dsql.DsqlSelectMetaDataFieldProperty/>
                        <org.mule.common.metadata.field.property.dsql.DsqlWhereMetaDataFieldProperty/>
                        <org.mule.common.metadata.field.property.dsql.DsqlOrderMetaDataFieldProperty/>
                        <org.mule.common.metadata.field.property.dsql.DsqlQueryOperatorsMetaDataFieldProperty>
                          <supportedOperators>
                            <org.mule.common.query.expression.LessOperator/>
                            <org.mule.common.query.expression.LessOrEqualsOperator/>
                            <org.mule.common.query.expression.EqualsOperator/>
                            <org.mule.common.query.expression.GreaterOperator/>
                            <org.mule.common.query.expression.GreaterOrEqualsOperator/>
                            <org.mule.common.query.expression.NotEqualsOperator/>
                            <org.mule.common.query.expression.LikeOperator/>
                          </supportedOperators>
                        </org.mule.common.metadata.field.property.dsql.DsqlQueryOperatorsMetaDataFieldProperty>
                      </properties>
                    </metaDataFieldPropertyManager>
                  </org.mule.common.metadata.DefaultMetaDataField>
                  <org.mule.common.metadata.DefaultMetaDataField>
                    <name>name</name>
                    <model class="org.mule.common.metadata.DefaultSimpleMetaDataModel" reference="../../org.mule.common.metadata.DefaultMetaDataField/model"/>
                    <accessType>READ_WRITE</accessType>
                    <metaDataFieldPropertyManager>
                      <properties>
                        <org.mule.common.metadata.field.property.dsql.DsqlSelectMetaDataFieldProperty/>
                        <org.mule.common.metadata.field.property.dsql.DsqlWhereMetaDataFieldProperty/>
                        <org.mule.common.metadata.field.property.dsql.DsqlOrderMetaDataFieldProperty/>
                        <org.mule.common.metadata.field.property.dsql.DsqlQueryOperatorsMetaDataFieldProperty>
                          <supportedOperators>
                            <org.mule.common.query.expression.LessOperator/>
                            <org.mule.common.query.expression.LessOrEqualsOperator/>
                            <org.mule.common.query.expression.EqualsOperator/>
                            <org.mule.common.query.expression.GreaterOperator/>
                            <org.mule.common.query.expression.GreaterOrEqualsOperator/>
                            <org.mule.common.query.expression.NotEqualsOperator/>
                            <org.mule.common.query.expression.LikeOperator/>
                          </supportedOperators>
                        </org.mule.common.metadata.field.property.dsql.DsqlQueryOperatorsMetaDataFieldProperty>
                      </properties>
                    </metaDataFieldPropertyManager>
                  </org.mule.common.metadata.DefaultMetaDataField>
                  <org.mule.common.metadata.DefaultMetaDataField>
                    <name>accountstatuscode</name>
                    <model class="org.mule.common.metadata.DefaultSimpleMetaDataModel" reference="../../org.mule.common.metadata.DefaultMetaDataField/model"/>
                    <accessType>READ_WRITE</accessType>
                    <metaDataFieldPropertyManager>
                      <properties>
                        <org.mule.common.metadata.field.property.dsql.DsqlSelectMetaDataFieldProperty/>
                        <org.mule.common.metadata.field.property.dsql.DsqlWhereMetaDataFieldProperty/>
                        <org.mule.common.metadata.field.property.dsql.DsqlOrderMetaDataFieldProperty/>
                        <org.mule.common.metadata.field.property.dsql.DsqlQueryOperatorsMetaDataFieldProperty>
                          <supportedOperators>
                            <org.mule.common.query.expression.LessOperator/>
                            <org.mule.common.query.expression.LessOrEqualsOperator/>
                            <org.mule.common.query.expression.EqualsOperator/>
                            <org.mule.common.query.expression.GreaterOperator/>
                            <org.mule.common.query.expression.GreaterOrEqualsOperator/>
                            <org.mule.common.query.expression.NotEqualsOperator/>
                            <org.mule.common.query.expression.LikeOperator/>
                          </supportedOperators>
                        </org.mule.common.metadata.field.property.dsql.DsqlQueryOperatorsMetaDataFieldProperty>
                      </properties>
                    </metaDataFieldPropertyManager>
                  </org.mule.common.metadata.DefaultMetaDataField>
                  <org.mule.common.metadata.DefaultMetaDataField>
                    <name>phoneno</name>
                    <model class="org.mule.common.metadata.DefaultSimpleMetaDataModel" reference="../../org.mule.common.metadata.DefaultMetaDataField/model"/>
                    <accessType>READ_WRITE</accessType>
                    <metaDataFieldPropertyManager>
                      <properties>
                        <org.mule.common.metadata.field.property.dsql.DsqlSelectMetaDataFieldProperty/>
                        <org.mule.common.metadata.field.property.dsql.DsqlWhereMetaDataFieldProperty/>
                        <org.mule.common.metadata.field.property.dsql.DsqlOrderMetaDataFieldProperty/>
                        <org.mule.common.metadata.field.property.dsql.DsqlQueryOperatorsMetaDataFieldProperty>
                          <supportedOperators>
                            <org.mule.common.query.expression.LessOperator/>
                            <org.mule.common.query.expression.LessOrEqualsOperator/>
                            <org.mule.common.query.expression.EqualsOperator/>
                            <org.mule.common.query.expression.GreaterOperator/>
                            <org.mule.common.query.expression.GreaterOrEqualsOperator/>
                            <org.mule.common.query.expression.NotEqualsOperator/>
                            <org.mule.common.query.expression.LikeOperator/>
                          </supportedOperators>
                        </org.mule.common.metadata.field.property.dsql.DsqlQueryOperatorsMetaDataFieldProperty>
                      </properties>
                    </metaDataFieldPropertyManager>
                  </org.mule.common.metadata.DefaultMetaDataField>
                </fields>
              </payload>
              <properties>
                <entry>
                  <org.mule.common.metadata.MetaDataPropertyScope>FLOW</org.mule.common.metadata.MetaDataPropertyScope>
                  <org.mule.common.metadata.MetaDataProperties>
                    <fields/>
                  </org.mule.common.metadata.MetaDataProperties>
                </entry>
                <entry>
                  <org.mule.common.metadata.MetaDataPropertyScope>INBOUND</org.mule.common.metadata.MetaDataPropertyScope>
                  <org.mule.common.metadata.MetaDataProperties>
                    <fields/>
                  </org.mule.common.metadata.MetaDataProperties>
                </entry>
                <entry>
                  <org.mule.common.metadata.MetaDataPropertyScope>RECORD</org.mule.common.metadata.MetaDataPropertyScope>
                  <org.mule.common.metadata.MetaDataProperties>
                    <fields/>
                  </org.mule.common.metadata.MetaDataProperties>
                </entry>
                <entry>
                  <org.mule.common.metadata.MetaDataPropertyScope>OUTBOUND</org.mule.common.metadata.MetaDataPropertyScope>
                  <org.mule.common.metadata.MetaDataProperties>
                    <fields/>
                  </org.mule.common.metadata.MetaDataProperties>
                </entry>
                <entry>
                  <org.mule.common.metadata.MetaDataPropertyScope>SESSION</org.mule.common.metadata.MetaDataPropertyScope>
                  <org.mule.common.metadata.MetaDataProperties>
                    <fields/>
                  </org.mule.common.metadata.MetaDataProperties>
                </entry>
              </properties>
            </input>
            <output class="org.mule.common.metadata.DefaultMetaData">
              <payload class="org.mule.common.metadata.DefaultSimpleMetaDataModel">
                <dataType>DOUBLE</dataType>
                <metaDataModelPropertiesManager>
                  <properties/>
                </metaDataModelPropertiesManager>
              </payload>
              <properties>
                <entry>
                  <org.mule.common.metadata.MetaDataPropertyScope>FLOW</org.mule.common.metadata.MetaDataPropertyScope>
                  <org.mule.common.metadata.MetaDataProperties>
                    <fields/>
                  </org.mule.common.metadata.MetaDataProperties>
                </entry>
                <entry>
                  <org.mule.common.metadata.MetaDataPropertyScope>INBOUND</org.mule.common.metadata.MetaDataPropertyScope>
                  <org.mule.common.metadata.MetaDataProperties>
                    <fields/>
                  </org.mule.common.metadata.MetaDataProperties>
                </entry>
                <entry>
                  <org.mule.common.metadata.MetaDataPropertyScope>RECORD</org.mule.common.metadata.MetaDataPropertyScope>
                  <org.mule.common.metadata.MetaDataProperties>
                    <fields/>
                  </org.mule.common.metadata.MetaDataProperties>
                </entry>
                <entry>
                  <org.mule.common.metadata.MetaDataPropertyScope>OUTBOUND</org.mule.common.metadata.MetaDataPropertyScope>
                  <org.mule.common.metadata.MetaDataProperties>
                    <fields/>
                  </org.mule.common.metadata.MetaDataProperties>
                </entry>
                <entry>
                  <org.mule.common.metadata.MetaDataPropertyScope>SESSION</org.mule.common.metadata.MetaDataPropertyScope>
                  <org.mule.common.metadata.MetaDataProperties>
                    <fields/>
                  </org.mule.common.metadata.MetaDataProperties>
                </entry>
              </properties>
            </output>
          </org.mule.tooling.metadata.cache.DefaultMetadataCacheEntry>
        </entry>
        <entry>
          <string>Insert into SellTo_Srini values (#[payload.]</string>
          <org.mule.tooling.metadata.cache.DefaultMetadataCacheEntry>
            <input class="org.mule.common.metadata.DefaultMetaData">
              <payload class="org.mule.common.metadata.DefaultDefinedMapMetaDataModel">
                <dataType>MAP</dataType>
                <metaDataModelPropertiesManager>
                  <properties/>
                </metaDataModelPropertiesManager>
                <fields>
                  <org.mule.common.metadata.DefaultMetaDataField>
                    <name></name>
                    <model class="org.mule.common.metadata.DefaultSimpleMetaDataModel">
                      <dataType>STRING</dataType>
                      <metaDataModelPropertiesManager>
                        <properties/>
                      </metaDataModelPropertiesManager>
                    </model>
                    <accessType>READ_WRITE</accessType>
                    <metaDataFieldPropertyManager>
                      <properties>
                        <org.mule.common.metadata.field.property.dsql.DsqlSelectMetaDataFieldProperty/>
                        <org.mule.common.metadata.field.property.dsql.DsqlWhereMetaDataFieldProperty/>
                        <org.mule.common.metadata.field.property.dsql.DsqlOrderMetaDataFieldProperty/>
                        <org.mule.common.metadata.field.property.dsql.DsqlQueryOperatorsMetaDataFieldProperty>
                          <supportedOperators>
                            <org.mule.common.query.expression.LessOperator/>
                            <org.mule.common.query.expression.LessOrEqualsOperator/>
                            <org.mule.common.query.expression.EqualsOperator/>
                            <org.mule.common.query.expression.GreaterOperator/>
                            <org.mule.common.query.expression.GreaterOrEqualsOperator/>
                            <org.mule.common.query.expression.NotEqualsOperator/>
                            <org.mule.common.query.expression.LikeOperator/>
                          </supportedOperators>
                        </org.mule.common.metadata.field.property.dsql.DsqlQueryOperatorsMetaDataFieldProperty>
                      </properties>
                    </metaDataFieldPropertyManager>
                  </org.mule.common.metadata.DefaultMetaDataField>
                </fields>
              </payload>
              <properties>
                <entry>
                  <org.mule.common.metadata.MetaDataPropertyScope>FLOW</org.mule.common.metadata.MetaDataPropertyScope>
                  <org.mule.common.metadata.MetaDataProperties>
                    <fields/>
                  </org.mule.common.metadata.MetaDataProperties>
                </entry>
                <entry>
                  <org.mule.common.metadata.MetaDataPropertyScope>INBOUND</org.mule.common.metadata.MetaDataPropertyScope>
                  <org.mule.common.metadata.MetaDataProperties>
                    <fields/>
                  </org.mule.common.metadata.MetaDataProperties>
                </entry>
                <entry>
                  <org.mule.common.metadata.MetaDataPropertyScope>RECORD</org.mule.common.metadata.MetaDataPropertyScope>
                  <org.mule.common.metadata.MetaDataProperties>
                    <fields/>
                  </org.mule.common.metadata.MetaDataProperties>
                </entry>
                <entry>
                  <org.mule.common.metadata.MetaDataPropertyScope>OUTBOUND</org.mule.common.metadata.MetaDataPropertyScope>
                  <org.mule.common.metadata.MetaDataProperties>
                    <fields/>
                  </org.mule.common.metadata.MetaDataProperties>
                </entry>
                <entry>
                  <org.mule.common.metadata.MetaDataPropertyScope>SESSION</org.mule.common.metadata.MetaDataPropertyScope>
                  <org.mule.common.metadata.MetaDataProperties>
                    <fields/>
                  </org.mule.common.metadata.MetaDataProperties>
                </entry>
              </properties>
            </input>
            <output class="org.mule.common.metadata.DefaultMetaData">
              <payload class="org.mule.common.metadata.DefaultSimpleMetaDataModel">
                <dataType>DOUBLE</dataType>
                <metaDataModelPropertiesManager>
                  <properties/>
                </metaDataModelPropertiesManager>
              </payload>
              <properties>
                <entry>
                  <org.mule.common.metadata.MetaDataPropertyScope>FLOW</org.mule.common.metadata.MetaDataPropertyScope>
                  <org.mule.common.metadata.MetaDataProperties>
                    <fields/>
                  </org.mule.common.metadata.MetaDataProperties>
                </entry>
                <entry>
                  <org.mule.common.metadata.MetaDataPropertyScope>INBOUND</org.mule.common.metadata.MetaDataPropertyScope>
                  <org.mule.common.metadata.MetaDataProperties>
                    <fields/>
                  </org.mule.common.metadata.MetaDataProperties>
                </entry>
                <entry>
                  <org.mule.common.metadata.MetaDataPropertyScope>RECORD</org.mule.common.metadata.MetaDataPropertyScope>
                  <org.mule.common.metadata.MetaDataProperties>
                    <fields/>
                  </org.mule.common.metadata.MetaDataProperties>
                </entry>
                <entry>
                  <org.mule.common.metadata.MetaDataPropertyScope>OUTBOUND</org.mule.common.metadata.MetaDataPropertyScope>
                  <org.mule.common.metadata.MetaDataProperties>
                    <fields/>
                  </org.mule.common.metadata.MetaDataProperties>
                </entry>
                <entry>
                  <org.mule.common.metadata.MetaDataPropertyScope>SESSION</org.mule.common.metadata.MetaDataPropertyScope>
                  <org.mule.common.metadata.MetaDataProperties>
                    <fields/>
                  </org.mule.common.metadata.MetaDataProperties>
                </entry>
              </properties>
            </output>
          </org.mule.tooling.metadata.cache.DefaultMetadataCacheEntry>
        </entry>
        <entry>
          <string>Insert into SellTo_Srini(No,Name,City,Postcode,PhoneNumber,AccountStatusCode,BilltoCustomer,SalespersonCode,LastDateModified,PriceCardCode) values(#[payload.No],#[payl.oad.Name],#[payload.City],#[payload.Postcode],#[payload.PhoneNumber],#[payload.AccountStatusCode],#[payload.BilltoCustomer],#[payload.SalespersonCode],#[payload.LastDateModified],#[payload.PriceCardCode])</string>
          <org.mule.tooling.metadata.cache.DefaultMetadataCacheEntry>
            <output class="org.mule.common.metadata.DefaultMetaData">
              <payload class="org.mule.common.metadata.DefaultSimpleMetaDataModel">
                <dataType>DOUBLE</dataType>
                <metaDataModelPropertiesManager>
                  <properties/>
                </metaDataModelPropertiesManager>
              </payload>
              <properties>
                <entry>
                  <org.mule.common.metadata.MetaDataPropertyScope>FLOW</org.mule.common.metadata.MetaDataPropertyScope>
                  <org.mule.common.metadata.MetaDataProperties>
                    <fields/>
                  </org.mule.common.metadata.MetaDataProperties>
                </entry>
                <entry>
                  <org.mule.common.metadata.MetaDataPropertyScope>INBOUND</org.mule.common.metadata.MetaDataPropertyScope>
                  <org.mule.common.metadata.MetaDataProperties>
                    <fields/>
                  </org.mule.common.metadata.MetaDataProperties>
                </entry>
                <entry>
                  <org.mule.common.metadata.MetaDataPropertyScope>RECORD</org.mule.common.metadata.MetaDataPropertyScope>
                  <org.mule.common.metadata.MetaDataProperties>
                    <fields/>
                  </org.mule.common.metadata.MetaDataProperties>
                </entry>
                <entry>
                  <org.mule.common.metadata.MetaDataPropertyScope>OUTBOUND</org.mule.common.metadata.MetaDataPropertyScope>
                  <org.mule.common.metadata.MetaDataProperties>
                    <fields/>
                  </org.mule.common.metadata.MetaDataProperties>
                </entry>
                <entry>
                  <org.mule.common.metadata.MetaDataPropertyScope>SESSION</org.mule.common.metadata.MetaDataPropertyScope>
                  <org.mule.common.metadata.MetaDataProperties>
                    <fields/>
                  </org.mule.common.metadata.MetaDataProperties>
                </entry>
              </properties>
            </output>
          </org.mule.tooling.metadata.cache.DefaultMetadataCacheEntry>
        </entry>
      </map>
    </entry>
  </metadataIo>
</metadata__cache__entry>